yourdb/__init__.py
yourdb/compaction.py
yourdb/entity.py
yourdb/locking.py
yourdb/utils.py
yourdb/yourdb.py
yourdb-0.2.1.dist-info/licenses/LICENSE
yourdb-0.2.1.dist-info/METADATA
yourdb-0.2.1.dist-info/WHEEL
yourdb-0.2.1.dist-info/top_level.txt
yourdb-0.2.1.dist-info/RECORD
