Metadata-Version: 2.4
Name: yourdb
Version: 0.2.1
Summary: A Python-native object database
Author-email: Dhruv Verma <engdhruv25@example.com>, Aayushman Gupta <aayushmangupta780@example.com>
License: MIT
Project-URL: Homepage, https://github.com/Dhruv251004/yourdb
Project-URL: Documentation, https://your-db-official-docs.vercel.app/
Project-URL: Repository, https://github.com/Dhruv251004/yourdb
Classifier: Programming Language :: Python :: 3
Classifier: Operating System :: OS Independent
Requires-Python: >=3.8
License-File: LICENSE
Dynamic: license-file
